CHANGELOG.md
LICENSE
whiteless/__init__.py
whiteless/templatetags/__init__.py
whiteless/templatetags/whiteless.py
django_whiteless-1.0.0.dist-info/LICENSE
django_whiteless-1.0.0.dist-info/WHEEL
django_whiteless-1.0.0.dist-info/METADATA
django_whiteless-1.0.0.dist-info/RECORD
