Metadata-Version: 2.1
Name: django-whiteless
Version: 1.0.0
Summary: Django template tags for dealing with pesky whitespaces
Home-page: https://github.com/denizdogan/django-whiteless
License: MIT
Keywords: django,whitespace,template,tag
Author: Deniz Dogan
Author-email: denizdogan@users.noreply.github.com
Requires-Python: >=3.7,<4.0
Classifier: Development Status :: 5 - Production/Stable
Classifier: Framework :: Django
Classifier: Framework :: Django :: 2.0
Classifier: Framework :: Django :: 2.1
Classifier: Framework :: Django :: 2.2
Classifier: Framework :: Django :: 3.0
Classifier: Framework :: Django :: 3.1
Classifier: Framework :: Django :: 3.2
Classifier: Intended Audience :: Developers
Classifier: License :: OSI Approved :: MIT License
Classifier: Programming Language :: Python :: 3
Classifier: Programming Language :: Python :: 3.7
Classifier: Programming Language :: Python :: 3.8
Classifier: Programming Language :: Python :: 3.9
Requires-Dist: Django (>=2.0,<4.0)
Project-URL: Documentation, https://github.com/denizdogan/django-whiteless
Project-URL: Repository, https://github.com/denizdogan/django-whiteless.git
